Ester/__init__.py
Ester/_version.py
Ester/data/ester1.dev.lst
Ester/data/ester1.dev.mdtm
Ester/data/ester1.dev.uem
Ester/data/ester1.trn.lst
Ester/data/ester1.trn.mdtm
Ester/data/ester1.trn.uem
Ester/data/ester1.tst.lst
Ester/data/ester1.tst.mdtm
Ester/data/ester1.tst.uem
Ester/data/ester2.dev.lst
Ester/data/ester2.dev.mdtm
Ester/data/ester2.dev.uem
Ester/data/ester2.trn.lst
Ester/data/ester2.trn.mdtm
Ester/data/ester2.trn.uem
Ester/data/ester2.tst.lst
Ester/data/ester2.tst.mdtm
Ester/data/ester2.tst.uem
pyannote.db.ester-0.1.dist-info/DESCRIPTION.rst
pyannote.db.ester-0.1.dist-info/entry_points.txt
pyannote.db.ester-0.1.dist-info/METADATA
pyannote.db.ester-0.1.dist-info/metadata.json
pyannote.db.ester-0.1.dist-info/RECORD
pyannote.db.ester-0.1.dist-info/top_level.txt
pyannote.db.ester-0.1.dist-info/WHEEL
